leakify.py
leakify-1.2.6.dist-info/METADATA
leakify-1.2.6.dist-info/WHEEL
leakify-1.2.6.dist-info/entry_points.txt
leakify-1.2.6.dist-info/top_level.txt
leakify-1.2.6.dist-info/RECORD
