Metadata-Version: 2.4
Name: leakify
Version: 1.2.6
Summary: Download photos and videos from leakedzone.com
Home-page: https://github.com/andrilchakraborty/leakify
Author: Cassidy
License: MIT
Requires-Python: >=3.7
Requires-Dist: aiohttp
Requires-Dist: beautifulsoup4
Requires-Dist: tabulate
Requires-Dist: colorama
